odoo/addons/femprocomuns/__init__.py
odoo/addons/femprocomuns/__manifest__.py
odoo/addons/femprocomuns/controllers/__init__.py
odoo/addons/femprocomuns/controllers/website_subscription.py
odoo/addons/femprocomuns/models/__init__.py
odoo/addons/femprocomuns/models/subscription_request.py
odoo/addons/femprocomuns/views/subscription_request_view.xml
odoo/addons/femprocomuns/views/subscription_template.xml
odoo12_addon_femprocomuns-12.0.1.2.2.dist-info/METADATA
odoo12_addon_femprocomuns-12.0.1.2.2.dist-info/WHEEL
odoo12_addon_femprocomuns-12.0.1.2.2.dist-info/top_level.txt
odoo12_addon_femprocomuns-12.0.1.2.2.dist-info/RECORD
